uiax/__init__.py
uiax/client.py
uiax/utils.py
uiax-0.1.5.dist-info/METADATA
uiax-0.1.5.dist-info/WHEEL
uiax-0.1.5.dist-info/RECORD
